typedpath/__init__.py
typedpath/args.py
typedpath/base.py
typedpath/bytes.py
typedpath/dict.py
typedpath/inspect.py
typedpath/json.py
typedpath/keycodec.py
typedpath/numpy.py
typedpath/pandas.py
typedpath/pickle.py
typedpath/py.typed
typedpath/struct.py
typedpath/text.py
typedpath-0.1.2.dist-info/LICENSE
typedpath-0.1.2.dist-info/METADATA
typedpath-0.1.2.dist-info/WHEEL
typedpath-0.1.2.dist-info/RECORD
