Metadata-Version: 2.1
Name: typedpath
Version: 0.1.2
Summary: Use typed Python objects to represent files and directories.
Home-page: https://github.com/jesnie/typedpath
License: MIT
Author: Jesper Nielsen
Author-email: jespernielsen1982+typedpath@gmail.com
Requires-Python: >=3.10,<4
Classifier: Development Status :: 4 - Beta
Classifier: Intended Audience :: Developers
Classifier: License :: OSI Approved :: MIT License
Classifier: Programming Language :: Python :: 3
Classifier: Programming Language :: Python :: 3.10
Classifier: Programming Language :: Python :: 3.11
Classifier: Programming Language :: Python :: 3.12
Classifier: Programming Language :: Python :: 3.13
Classifier: Typing :: Typed
Provides-Extra: numpy
Provides-Extra: pandas
Requires-Dist: numpy (>=1.26.0,<3) ; extra == "numpy"
Requires-Dist: pandas (>=2.0.0,<3) ; extra == "pandas"
Requires-Dist: pyarrow (>=14.0.0,<19) ; extra == "pandas"
Project-URL: Repository, https://github.com/jesnie/typedpath
